YAPM/Matrix.py
YAPM/Other.py
YAPM/__init__.py
YetAnotherModule-0.0.2.3.dist-info/LICENSE
YetAnotherModule-0.0.2.3.dist-info/METADATA
YetAnotherModule-0.0.2.3.dist-info/WHEEL
YetAnotherModule-0.0.2.3.dist-info/top_level.txt
YetAnotherModule-0.0.2.3.dist-info/RECORD
