Metadata-Version: 2.1
Name: YetAnotherModule
Version: 0.0.2.3
Summary: Yet Another Python Module.
Home-page: https://github.com/carson-coder/Yet-Another-Python-Module
Author: Carson
Author-email: carsondpool@gmail.com
License: LICENSE
Requires-Python: >=3.10
License-File: LICENSE
